experiment_utils/__init__.py
experiment_utils/_nbdev.py
experiment_utils/consistency.py
experiment_utils/data_imagenette.py
experiment_utils/experiment.py
experiment_utils/ranger.py
experiment_utils/utils.py
experiment_utils-0.0.3.dist-info/LICENSE
experiment_utils-0.0.3.dist-info/METADATA
experiment_utils-0.0.3.dist-info/WHEEL
experiment_utils-0.0.3.dist-info/entry_points.txt
experiment_utils-0.0.3.dist-info/top_level.txt
experiment_utils-0.0.3.dist-info/RECORD
