Metadata-Version: 2.1
Name: experiment-utils
Version: 0.0.3
Summary: Helpers utils for manage and track experiments.
Home-page: https://github.com/ayasyrev/experiment_utils
Author: Andrei Yasyrev
Author-email: a.yasyrev@gmail.com
License: Apache Software License 2.0
Keywords: DL pytorch experiment
Platform: UNKNOWN
Classifier: Development Status :: 3 - Alpha
Classifier: Intended Audience :: Developers
Classifier: License :: OSI Approved :: Apache Software License
Classifier: Natural Language :: English
Classifier: Programming Language :: Python :: 3.6
Classifier: Programming Language :: Python :: 3.7
Classifier: Programming Language :: Python :: 3.8
Requires-Python: >=3.6
Requires-Dist: fastcore
Requires-Dist: torch
Requires-Dist: fastai
